prisma2markdown/__init__.py
prisma2markdown/cli.py
prisma2markdown/mermaid.py
prisma2markdown/model.py
prisma2markdown/relations.py
prisma2markdown/workflow.py
prisma2markdown-1.0.5.dist-info/LICENSE
prisma2markdown-1.0.5.dist-info/METADATA
prisma2markdown-1.0.5.dist-info/WHEEL
prisma2markdown-1.0.5.dist-info/entry_points.txt
prisma2markdown-1.0.5.dist-info/top_level.txt
prisma2markdown-1.0.5.dist-info/RECORD
