Metadata-Version: 2.1
Name: prisma2markdown
Version: 1.0.5
Summary: A pure python mermaid generator for prisma schema.
Author-email: HO Olivier <hozhenwai@gmail.com>
Project-URL: Source, https://github.com/HOZHENWAI/py-prisma2markdown
Requires-Python: >=3.10
License-File: LICENSE
Requires-Dist: structlog
Requires-Dist: click
